{
  "_fv": 28,
  "_type": "loottable",
  "definition": {
    "type": "Block",
    "pools": [
      {
        "minrolls": 1,
        "maxrolls": 1,
        "minbonusrolls": 1,
        "maxbonusrolls": 1,
        "hasbonusrolls": false,
        "entries": [
          {
            "type": "item",
            "item": {
              "value": "CUSTOM:EfowWeedBubbly"
            },
            "weight": 1,
            "minCount": 1,
            "maxCount": 1,
            "minEnchantmentLevel": 0,
            "maxEnchantmentLevel": 0,
            "affectedByFortune": false,
            "explosionDecay": false,
            "silkTouchMode": 1
          }
        ]
      },
      {
        "minrolls": 1,
        "maxrolls": 1,
        "minbonusrolls": 1,
        "maxbonusrolls": 1,
        "hasbonusrolls": false,
        "entries": [
          {
            "type": "item",
            "item": {
              "value": "CUSTOM:EfowWeed"
            },
            "weight": 1,
            "minCount": 1,
            "maxCount": 1,
            "minEnchantmentLevel": 0,
            "maxEnchantmentLevel": 0,
            "affectedByFortune": false,
            "explosionDecay": false,
            "silkTouchMode": 2
          }
        ]
      },
      {
        "minrolls": 1,
        "maxrolls": 1,
        "minbonusrolls": 1,
        "maxbonusrolls": 1,
        "hasbonusrolls": false,
        "entries": [
          {
            "type": "item",
            "item": {
              "value": "CUSTOM:EfowFruit"
            },
            "weight": 1,
            "minCount": 1,
            "maxCount": 1,
            "minEnchantmentLevel": 0,
            "maxEnchantmentLevel": 0,
            "affectedByFortune": false,
            "explosionDecay": false,
            "silkTouchMode": 2
          }
        ]
      }
    ],
    "name": "blocks/efow_weed_bubbly",
    "namespace": "mod"
  }
}