{
  "_fv": 24,
  "_type": "livingentity",
  "definition": {
    "mobName": "Infected Rock",
    "mobLabel": "",
    "mobModelName": "Modelinfested_rock",
    "mobModelTexture": "infectedrock2.png",
    "mobModelGlowTexture": "",
    "modelWidth": 0.6,
    "modelHeight": 1.8,
    "modelShadowSize": 0.5,
    "mountedYOffset": 0.0,
    "hasSpawnEgg": true,
    "spawnEggBaseColor": {
      "value": -11713203,
      "falpha": 0.0
    },
    "spawnEggDotColor": {
      "value": -3380171,
      "falpha": 0.0
    },
    "creativeTab": {
      "value": "CUSTOM:TranscendeumMobs"
    },
    "isBoss": false,
    "bossBarColor": "PINK",
    "bossBarType": "PROGRESS",
    "equipmentMainHand": {
      "value": ""
    },
    "equipmentOffHand": {
      "value": ""
    },
    "equipmentHelmet": {
      "value": ""
    },
    "equipmentBody": {
      "value": ""
    },
    "equipmentLeggings": {
      "value": ""
    },
    "equipmentBoots": {
      "value": ""
    },
    "mobBehaviourType": "Mob",
    "mobCreatureType": "UNDEFINED",
    "attackStrength": 1,
    "attackKnockback": 0.0,
    "knockbackResistance": 0.6,
    "movementSpeed": 0.01,
    "armorBaseValue": 1.0,
    "trackingRange": 64,
    "health": 10,
    "xpAmount": 0,
    "waterMob": false,
    "flyingMob": false,
    "guiBoundTo": "<NONE>",
    "inventorySize": 9,
    "inventoryStackSize": 64,
    "disableCollisions": false,
    "ridable": false,
    "canControlForward": false,
    "canControlStrafe": false,
    "immuneToFire": false,
    "immuneToArrows": true,
    "immuneToFallDamage": false,
    "immuneToCactus": false,
    "immuneToDrowning": false,
    "immuneToLightning": false,
    "immuneToPotions": false,
    "immuneToPlayer": false,
    "immuneToExplosion": false,
    "immuneToTrident": false,
    "immuneToAnvil": false,
    "immuneToWither": false,
    "immuneToDragonBreath": false,
    "mobDrop": {
      "value": ""
    },
    "livingSound": {
      "value": ""
    },
    "hurtSound": {
      "value": "block.stone.break"
    },
    "deathSound": {
      "value": "block.stone.break"
    },
    "stepSound": {
      "value": ""
    },
    "spawnParticles": false,
    "particleToSpawn": {
      "value": "CUSTOM:Twilighteris"
    },
    "particleSpawningShape": "Spread",
    "particleSpawningRadious": 0.5,
    "particleAmount": 4,
    "whenMobDies": {
      "name": "InfectedRockEntityDies"
    },
    "whenMobIsHurt": {
      "name": "InfectedRockEntityIsHurt"
    },
    "hasAI": true,
    "aiBase": "(none)",
    "aixml": "<xml xmlns=\"https://developers.google.com/blockly/xml\"><block type=\"aitasks_container\" deletable=\"false\" x=\"124\" y=\"40\"><next><block type=\"attack_entity\"><field name=\"insight\">FALSE</field><field name=\"nearby\">FALSE</field><field name=\"entity\">EntityPlayer</field><field name=\"condition\">null,null</field><next><block type=\"look_around\"><field name=\"condition\">null,null</field></block></next></block></next></block></xml>",
    "breedable": false,
    "tameable": false,
    "breedTriggerItems": [],
    "ranged": true,
    "rangedAttackItem": {
      "value": "CUSTOM:ViridInfectionItem"
    },
    "rangedItemType": "Default item",
    "spawnThisMob": true,
    "doesDespawnWhenIdle": true,
    "spawningProbability": 15,
    "mobSpawningType": "creature",
    "minNumberOfMobsPerGroup": 1,
    "maxNumberOfMobsPerGroup": 2,
    "restrictionBiomes": [
      {
        "value": "CUSTOM:ViridianMires"
      }
    ],
    "spawnInDungeons": false
  }
}